databutton/__init__.py
databutton/internal/__init__.py
databutton/internal/auth.py
databutton/internal/dbapiclient.py
databutton/internal/httpxclient.py
databutton/internal/performedby.py
databutton/internal/retries.py
databutton/secrets/__init__.py
databutton/secrets/secrets.py
databutton/storage/__init__.py
databutton/storage/storage.py
databutton/version.py
databutton-0.40.0.dist-info/METADATA
databutton-0.40.0.dist-info/WHEEL
databutton-0.40.0.dist-info/licenses/LICENSE
databutton-0.40.0.dist-info/RECORD
