Metadata-Version: 2.4
Name: databutton
Version: 0.40.0
Summary: The CLI for databutton.com
License: Databutton
License-File: LICENSE
Author: Databutton
Author-email: hi@databutton.io
Requires-Python: >=3.10,<3.12
Classifier: License :: Other/Proprietary License
Classifier: Programming Language :: Python :: 3
Classifier: Programming Language :: Python :: 3.10
Classifier: Programming Language :: Python :: 3.11
Requires-Dist: PyJWT (>=2,<3)
Requires-Dist: PyYAML (>=6,<7)
Requires-Dist: certifi (>=2022.12.7,<2023.0.0)
Requires-Dist: cryptography (>=40)
Requires-Dist: fastapi
Requires-Dist: httpx (>=0.20.0,<1)
Requires-Dist: pandas[feather] (>=0.25,<3)
Requires-Dist: pydantic (>=1,<3)
Requires-Dist: tenacity (>=8.3)
